curtis/__init__.py
curtis/__main__.py
curtis/client.py
curtis/config.py
curtis/filters.py
curtis/models.py
curtis/output.py
curtis/utils.py
curtis-0.2.dist-info/DESCRIPTION.rst
curtis-0.2.dist-info/METADATA
curtis-0.2.dist-info/RECORD
curtis-0.2.dist-info/WHEEL
curtis-0.2.dist-info/entry_points.txt
curtis-0.2.dist-info/metadata.json
curtis-0.2.dist-info/top_level.txt
curtis-0.2.dist-info/zip-safe
