Metadata-Version: 2.0
Name: curtis
Version: 0.2
Summary: A simple sentry cli
Home-page: http://github.com/polyconseil/curtis
Author: Polyconseil
Author-email: opensource+curtis@polyconseil.fr
License: BSD 3-Clause License
Keywords: sentry,cli
Platform: UNKNOWN
Classifier: Development Status :: 5 - Production/Stable
Classifier: Environment :: Console
Classifier: Intended Audience :: Developers
Classifier: Intended Audience :: System Administrators
Classifier: License :: OSI Approved :: BSD License
Classifier: Natural Language :: English
Classifier: Operating System :: OS Independent
Classifier: Programming Language :: Python :: 3.4
Classifier: Programming Language :: Python :: 3.5
Classifier: Programming Language :: Python :: 3.6
Classifier: Programming Language :: Python :: 3.7
Classifier: Programming Language :: Python :: 3 :: Only
Classifier: Topic :: Software Development :: Bug Tracking
Classifier: Topic :: System :: Logging
Classifier: Topic :: Terminals
Classifier: Topic :: Utilities
Requires-Dist: click
Requires-Dist: requests
Requires-Dist: termcolor
